setup.py
./mangrove/__init__.py
./mangrove/constants.py
./mangrove/declarative.py
./mangrove/exceptions.py
./mangrove/mappings.py
./mangrove/pool.py
./mangrove/services.py
./mangrove/utils.py
pymangrove.egg-info/PKG-INFO
pymangrove.egg-info/SOURCES.txt
pymangrove.egg-info/dependency_links.txt
pymangrove.egg-info/requires.txt
pymangrove.egg-info/top_level.txt
pymangrove.egg-info/zip-safe