Metadata-Version: 1.0
Name: pymangrove
Version: 1.0.0
Summary: a boto connexion pool
Home-page: http://github.com/botify-labs/mangrove
Author: Oleiade
Author-email: theo@botify.com
License: MIT
Keywords: amazon aws boto python connexion pool
Platform: UNKNOWN
